PyTitanium/__init__.py
PyTitanium/locators.py
PyTitanium/titanium_core.py
PyTitanium-3.3.dist-info/LICENSE
PyTitanium-3.3.dist-info/METADATA
PyTitanium-3.3.dist-info/WHEEL
PyTitanium-3.3.dist-info/top_level.txt
PyTitanium-3.3.dist-info/RECORD
