Metadata-Version: 2.1
Name: PyTitanium
Version: 3.3
License-File: LICENSE
